README.md
setup.py
SQLAlchemy_Aide.egg-info/PKG-INFO
SQLAlchemy_Aide.egg-info/SOURCES.txt
SQLAlchemy_Aide.egg-info/dependency_links.txt
SQLAlchemy_Aide.egg-info/not-zip-safe
SQLAlchemy_Aide.egg-info/requires.txt
SQLAlchemy_Aide.egg-info/top_level.txt
example/__init__.py
example/app.py
sqlalchemy_aide/__init__.py
sqlalchemy_aide/database.py
sqlalchemy_aide/helpers.py
sqlalchemy_aide/processor.py
sqlalchemy_aide/transformer.py
sqlalchemy_aide/types.py
sqlalchemy_aide/mixins/__init__.py
sqlalchemy_aide/mixins/abstracts.py
sqlalchemy_aide/mixins/columns.py
sqlalchemy_aide/mixins/core.py